indextextreplace/README.MD
indextextreplace/__init__.py
indextextreplace/requirements.txt
indextextreplace/thirdparty.json
indextextreplace-0.10.dist-info/LICENSE.rst
indextextreplace-0.10.dist-info/METADATA
indextextreplace-0.10.dist-info/WHEEL
indextextreplace-0.10.dist-info/top_level.txt
indextextreplace-0.10.dist-info/RECORD
