Metadata-Version: 2.1
Name: indextextreplace
Version: 0.10
Summary: Replace specific substrings within a given string using index-based replacements
Home-page: https://github.com/hansalemaos/indextextreplace
Author: Johannes Fischer
Author-email: aulasparticularesdealemaosp@gmail.com
License: MIT
Keywords: string,replace
Classifier: Development Status :: 4 - Beta
Classifier: Programming Language :: Python :: 3 :: Only
Classifier: Programming Language :: Python :: 3.10
Classifier: Topic :: Software Development :: Libraries :: Python Modules
Classifier: Topic :: Utilities
License-File: LICENSE.rst
